tests/test_utils.py
voodoonet/__init__.py
voodoonet/datasets.py
voodoonet/loader.py
voodoonet/py.typed
voodoonet/torch_model.py
voodoonet/utils.py
voodoonet/version.py
voodoonet/trained_models/Vnet2_0-dy0.00-fnXX-cuda0.pt
voodoonet-0.1.11.dist-info/LICENSE
voodoonet-0.1.11.dist-info/METADATA
voodoonet-0.1.11.dist-info/WHEEL
voodoonet-0.1.11.dist-info/top_level.txt
voodoonet-0.1.11.dist-info/RECORD
