Metadata-Version: 2.2
Name: voodoonet
Version: 0.1.11
Summary: Machine learning application for detecting liquid droplets in mixed-phase clouds using Doppler cloud radar spectra
Author-email: Willi Schimmel <willi.schimmel@uni-leipzig.de>
License: MIT License
Project-URL: Bug Tracker, https://github.com/actris-cloudnet/voodoonet/issues
Project-URL: Changelog, https://github.com/actris-cloudnet/voodoonet/blob/main/CHANGELOG.md
Project-URL: Homepage, https://github.com/actris-cloudnet/voodoonet
Project-URL: Repository, https://github.com/actris-cloudnet/voodoonet
Classifier: Intended Audience :: Science/Research
Classifier: License :: OSI Approved :: MIT License
Classifier: Operating System :: OS Independent
Classifier: Programming Language :: Python :: 3.10
Classifier: Topic :: Scientific/Engineering
Requires-Python: >=3.10
License-File: LICENSE
Requires-Dist: numpy
Requires-Dist: rpgpy>=0.12.1
Requires-Dist: scipy
Requires-Dist: torchmetrics
Requires-Dist: tqdm
Requires-Dist: wandb
Provides-Extra: dev
Requires-Dist: mypy; extra == "dev"
Requires-Dist: pre-commit; extra == "dev"
Requires-Dist: pytest; extra == "dev"
Requires-Dist: pytest-flakefinder; extra == "dev"
Requires-Dist: release-version; extra == "dev"
Requires-Dist: ruff; extra == "dev"
Requires-Dist: types-requests; extra == "dev"
Requires-Dist: types-tqdm; extra == "dev"
